pDeepXL/__init__.py
pDeepXL/console_wapper.py
pDeepXL/featurer.py
pDeepXL/mass_util.py
pDeepXL/model.py
pDeepXL/plot.py
pDeepXL/predict.py
pDeepXL/utils.py
pDeepXL/configs/aa.ini
pDeepXL/configs/config.ini
pDeepXL/configs/element.ini
pDeepXL/examples/examples.zip
pDeepXL/examples/cleavable/data/clv_dataset.txt
pDeepXL/examples/non_cleavable/data/non_clv_dataset.txt
pDeepXL/pt/clv_model.pt
pDeepXL/pt/non_clv_model.pt
tests/__init__.py
tests/test_predict_batch.py
tests/test_predict_single.py
pDeepXL-1.2.0.dist-info/LICENSE
pDeepXL-1.2.0.dist-info/METADATA
pDeepXL-1.2.0.dist-info/WHEEL
pDeepXL-1.2.0.dist-info/entry_points.txt
pDeepXL-1.2.0.dist-info/top_level.txt
pDeepXL-1.2.0.dist-info/RECORD
