Metadata-Version: 2.1
Name: pDeepXL
Version: 1.2.0
Summary: MS/MS spectrum prediction for cross-linked peptide pairs by deep learning
Home-page: https://github.com/pFindStudio/pDeepXL
Author: Zhenlin Chen
Author-email: chenzhenlin@ict.ac.cn
License: UNKNOWN
Platform: UNKNOWN
Classifier: Programming Language :: Python :: 3
Classifier: License :: OSI Approved :: GNU General Public License v3 (GPLv3)
Classifier: Operating System :: OS Independent
Requires-Python: >=3.6
Requires-Dist: tqdm
Requires-Dist: numpy
Requires-Dist: matplotlib
Requires-Dist: seaborn
Requires-Dist: scikit-learn
Requires-Dist: scipy
Requires-Dist: torch
Requires-Dist: torchvision
